{
  "swagger": "2.0",
  "info": {
    "title": "Ticket Flow",
    "description": "Backend for Ticket Flow Application. Below you can find all API endpoints which are served on this server.",
    "version": "1.0.0"
  },
  "host": "localhost:5000",
  "basePath": "/",
  "schemes": [
    "http"
  ],
  "paths": {
    "/events": {
      "get": {
        "tags": [
          "Events"
        ],
        "description": "",
        "responses": {
          "200": {
            "description": "OK"
          },
          "500": {
            "description": "Internal Server Error"
          }
        }
      },
      "post": {
        "tags": [
          "Events"
        ],
        "description": "",
        "parameters": [
          {
            "name": "body",
            "in": "body",
            "schema": {
              "type": "object",
              "properties": {
                "title": {
                  "type": "string",
                  "example": "Anime simfonija"
                },
                "image": {
                  "type": "string",
                  "example": "https://assets.tickets.rs/123abc321/0/Images/a89db5f9-19dc-4a82-a684-3df4d51e2e8d___192x108.jpeg"
                },
                "location": {
                  "type": "string",
                  "example": "mts dvorana"
                },
                "link": {
                  "type": "string",
                  "example": "https://tickets.rs/event/anime_simfonija_9967"
                },
                "date": {
                  "type": "string",
                  "example": "26. april 2024."
                },
                "time": {
                  "type": "string",
                  "example": "20:00"
                },
                "category": {
                  "type": "string",
                  "example": "concert"
                }
              },
              "required": [
                "title",
                "image",
                "location",
                "link",
                "date",
                "time",
                "category"
              ]
            }
          }
        ],
        "responses": {
          "200": {
            "description": "OK"
          },
          "500": {
            "description": "Internal Server Error"
          }
        }
      }
    },
    "/events/category/{category}": {
      "get": {
        "tags": [
          "Events"
        ],
        "description": "",
        "parameters": [
          {
            "name": "category",
            "in": "path",
            "required": true,
            "type": "string"
          }
        ],
        "responses": {
          "200": {
            "description": "OK"
          },
          "500": {
            "description": "Internal Server Error"
          }
        }
      }
    },
    "/events/{id}": {
      "get": {
        "tags": [
          "Events"
        ],
        "description": "",
        "parameters": [
          {
            "name": "id",
            "in": "path",
            "required": true,
            "type": "string"
          }
        ],
        "responses": {
          "200": {
            "description": "OK"
          },
          "500": {
            "description": "Internal Server Error"
          }
        }
      },
      "patch": {
        "tags": [
          "Events"
        ],
        "description": "",
        "parameters": [
          {
            "name": "id",
            "in": "path",
            "required": true,
            "type": "string"
          },
          {
            "name": "body",
            "in": "body",
            "schema": {
              "type": "object",
              "properties": {
                "title": {
                  "type": "string",
                  "example": "Anime simfonija"
                },
                "image": {
                  "type": "string",
                  "example": "https://assets.tickets.rs/123abc321/0/Images/a89db5f9-19dc-4a82-a684-3df4d51e2e8d___192x108.jpeg"
                },
                "location": {
                  "type": "string",
                  "example": "mts dvorana"
                },
                "link": {
                  "type": "string",
                  "example": "https://tickets.rs/event/anime_simfonija_9967"
                },
                "date": {
                  "type": "string",
                  "example": "26. april 2024."
                },
                "time": {
                  "type": "string",
                  "example": "20:00"
                },
                "category": {
                  "type": "string",
                  "example": "concert"
                }
              },
              "required": [
                "title",
                "image",
                "location",
                "link",
                "date",
                "time",
                "category"
              ]
            }
          }
        ],
        "responses": {
          "200": {
            "description": "OK"
          },
          "500": {
            "description": "Internal Server Error"
          }
        }
      },
      "delete": {
        "tags": [
          "Events"
        ],
        "description": "",
        "parameters": [
          {
            "name": "id",
            "in": "path",
            "required": true,
            "type": "string"
          }
        ],
        "responses": {
          "200": {
            "description": "OK"
          },
          "500": {
            "description": "Internal Server Error"
          }
        }
      }
    },
    "/refresh-data": {
      "get": {
        "tags": [
          "Events"
        ],
        "description": "",
        "responses": {
          "200": {
            "description": "OK"
          }
        }
      }
    },
    "/events/search": {
      "post": {
        "tags": [
          "Events"
        ],
        "description": "",
        "parameters": [
          {
            "name": "body",
            "in": "body",
            "schema": {
              "type": "object",
              "properties": {
                "title": {
                  "type": "string",
                  "example": "par"
                },
                "category": {
                  "type": "string",
                  "example": "concert"
                },
                "location": {
                  "type": "string",
                  "example": "banovina"
                },
                "date": {
                  "type": "string",
                  "example": "2024"
                }
              },
              "required": [
                "title",
                "category",
                "location",
                "date"
              ]
            }
          }
        ],
        "responses": {
          "200": {
            "description": "OK"
          },
          "500": {
            "description": "Internal Server Error"
          }
        }
      }
    },
    "/users": {
      "get": {
        "tags": [
          "Users"
        ],
        "description": "",
        "responses": {
          "200": {
            "description": "OK"
          },
          "500": {
            "description": "Internal Server Error"
          }
        }
      },
      "post": {
        "tags": [
          "Users"
        ],
        "description": "",
        "parameters": [
          {
            "name": "body",
            "in": "body",
            "schema": {
              "type": "object",
              "properties": {
                "id": {
                  "type": "string",
                  "example": "user_29w83sxmDNGwOuEthce5gg56FcC"
                },
                "full_name": {
                  "type": "string",
                  "example": "John Doe"
                },
                "phone": {
                  "type": "string",
                  "example": "+1234567890"
                },
                "gender": {
                  "type": "string",
                  "example": "Male"
                },
                "is_verified": {
                  "type": "boolean",
                  "example": true
                },
                "personal_id": {
                  "type": "string",
                  "example": "1234567890"
                },
                "tickets_sold": {
                  "type": "number",
                  "example": 10
                },
                "is_reliable_seller": {
                  "type": "boolean",
                  "example": true
                },
                "bio": {
                  "type": "string",
                  "example": "Lorem ipsum dolor sit amet, consectetur adipiscing elit. Sed vitae libero nec odio vehicula semper eget sed nisi."
                },
                "email": {
                  "type": "string",
                  "example": "john.doe@gmail.com"
                },
                "image": {
                  "type": "string",
                  "example": "https://g.foolcdn.com/editorial/images/454506/smiling-man-in-suit_gettyimages-509102308.jpg"
                }
              },
              "required": [
                "id",
                "full_name",
                "phone",
                "gender",
                "is_verified",
                "personal_id",
                "tickets_sold",
                "is_reliable_seller",
                "bio",
                "email",
                "image"
              ]
            }
          }
        ],
        "responses": {
          "200": {
            "description": "OK"
          },
          "500": {
            "description": "Internal Server Error"
          }
        }
      }
    },
    "/users/{id}": {
      "get": {
        "tags": [
          "Users"
        ],
        "description": "",
        "parameters": [
          {
            "name": "id",
            "in": "path",
            "required": true,
            "type": "string"
          }
        ],
        "responses": {
          "200": {
            "description": "OK"
          },
          "500": {
            "description": "Internal Server Error"
          }
        }
      },
      "patch": {
        "tags": [
          "Users"
        ],
        "description": "",
        "parameters": [
          {
            "name": "id",
            "in": "path",
            "required": true,
            "type": "string"
          },
          {
            "name": "body",
            "in": "body",
            "schema": {
              "type": "object",
              "properties": {
                "full_name": {
                  "type": "string",
                  "example": "John Doe 2"
                },
                "phone": {
                  "type": "string",
                  "example": "+1234567890"
                },
                "gender": {
                  "type": "string",
                  "example": "Male"
                },
                "is_verified": {
                  "type": "boolean",
                  "example": true
                },
                "personal_id": {
                  "type": "string",
                  "example": "1234567890"
                },
                "tickets_sold": {
                  "type": "number",
                  "example": 10
                },
                "is_reliable_seller": {
                  "type": "boolean",
                  "example": true
                },
                "bio": {
                  "type": "string",
                  "example": "Lorem ipsum dolor sit amet, consectetur adipiscing elit. Sed vitae libero nec odio vehicula semper eget sed nisi."
                },
                "email": {
                  "type": "string",
                  "example": "john.doe@gmail.com"
                },
                "image": {
                  "type": "string",
                  "example": "https://g.foolcdn.com/editorial/images/454506/smiling-man-in-suit_gettyimages-509102308.jpg"
                }
              },
              "required": [
                "full_name",
                "phone",
                "gender",
                "is_verified",
                "personal_id",
                "tickets_sold",
                "is_reliable_seller",
                "bio",
                "email",
                "image"
              ]
            }
          }
        ],
        "responses": {
          "200": {
            "description": "OK"
          },
          "500": {
            "description": "Internal Server Error"
          }
        }
      },
      "delete": {
        "tags": [
          "Users"
        ],
        "description": "",
        "parameters": [
          {
            "name": "id",
            "in": "path",
            "required": true,
            "type": "string"
          }
        ],
        "responses": {
          "200": {
            "description": "OK"
          },
          "500": {
            "description": "Internal Server Error"
          }
        }
      }
    },
    "/offers": {
      "get": {
        "tags": [
          "Offers"
        ],
        "description": "",
        "responses": {
          "200": {
            "description": "OK"
          },
          "500": {
            "description": "Internal Server Error"
          }
        }
      },
      "post": {
        "tags": [
          "Offers"
        ],
        "description": "",
        "parameters": [
          {
            "name": "body",
            "in": "body",
            "schema": {
              "type": "object",
              "properties": {
                "event_id": {
                  "type": "number",
                  "example": 2
                },
                "price": {
                  "type": "number",
                  "example": 2000
                },
                "details": {
                  "type": "string",
                  "example": "The most popular festival in Eastern Europe and world"
                },
                "seat_number": {
                  "type": "string",
                  "example": "G12"
                },
                "seat_area": {
                  "type": "string",
                  "example": "South"
                },
                "seller_uid": {
                  "type": "number",
                  "example": 2
                },
                "status": {
                  "type": "string",
                  "example": "open"
                },
                "customer_uid": {
                  "type": "number",
                  "example": 1
                },
                "quantity": {
                  "type": "number",
                  "example": 1
                },
                "document_url": {
                  "type": "string",
                  "example": ""
                }
              },
              "required": [
                "event_id",
                "price",
                "details",
                "seat_number",
                "seat_area",
                "seller_uid",
                "status",
                "customer_uid",
                "quantity",
                "document_url"
              ]
            }
          }
        ],
        "responses": {
          "200": {
            "description": "OK"
          },
          "500": {
            "description": "Internal Server Error"
          }
        }
      }
    },
    "/offers/{id}": {
      "get": {
        "tags": [
          "Offers"
        ],
        "description": "",
        "parameters": [
          {
            "name": "id",
            "in": "path",
            "required": true,
            "type": "string"
          }
        ],
        "responses": {
          "200": {
            "description": "OK"
          },
          "500": {
            "description": "Internal Server Error"
          }
        }
      },
      "patch": {
        "tags": [
          "Offers"
        ],
        "description": "",
        "parameters": [
          {
            "name": "id",
            "in": "path",
            "required": true,
            "type": "string"
          },
          {
            "name": "body",
            "in": "body",
            "schema": {
              "type": "object",
              "properties": {
                "event_id": {
                  "type": "number",
                  "example": 2
                },
                "price": {
                  "type": "number",
                  "example": 3000
                },
                "details": {
                  "type": "string",
                  "example": "The most popular festival in Eastern Europe and world"
                },
                "seat_number": {
                  "type": "string",
                  "example": "G12"
                },
                "seat_area": {
                  "type": "string",
                  "example": "South"
                },
                "seller_uid": {
                  "type": "number",
                  "example": 2
                },
                "status": {
                  "type": "string",
                  "example": "open"
                },
                "customer_uid": {
                  "type": "number",
                  "example": 1
                },
                "quantity": {
                  "type": "number",
                  "example": 2
                },
                "document_url": {
                  "type": "string",
                  "example": ""
                }
              },
              "required": [
                "event_id",
                "price",
                "details",
                "seat_number",
                "seat_area",
                "seller_uid",
                "status",
                "customer_uid",
                "quantity",
                "document_url"
              ]
            }
          }
        ],
        "responses": {
          "200": {
            "description": "OK"
          },
          "500": {
            "description": "Internal Server Error"
          }
        }
      },
      "delete": {
        "tags": [
          "Offers"
        ],
        "description": "",
        "parameters": [
          {
            "name": "id",
            "in": "path",
            "required": true,
            "type": "string"
          }
        ],
        "responses": {
          "200": {
            "description": "OK"
          },
          "500": {
            "description": "Internal Server Error"
          }
        }
      }
    },
    "/offers/events/{id}": {
      "get": {
        "tags": [
          "Offers"
        ],
        "description": "",
        "parameters": [
          {
            "name": "id",
            "in": "path",
            "required": true,
            "type": "string"
          }
        ],
        "responses": {
          "200": {
            "description": "OK"
          },
          "500": {
            "description": "Internal Server Error"
          }
        }
      }
    },
    "/order": {
      "post": {
        "tags": [
          "Order"
        ],
        "description": "",
        "parameters": [
          {
            "name": "body",
            "in": "body",
            "schema": {
              "type": "object",
              "properties": {
                "to": {
                  "type": "string",
                  "example": "ticket.flow.development@gmail.com"
                },
                "full_name": {
                  "type": "string",
                  "example": "Nikola Mirilo"
                },
                "orders": {
                  "type": "array",
                  "items": {
                    "type": "object",
                    "properties": {
                      "event_title": {
                        "type": "string",
                        "example": "AC/DC"
                      },
                      "seller_full_name": {
                        "type": "string",
                        "example": "Pera Peric"
                      },
                      "seller_email": {
                        "type": "string",
                        "example": "peraperic@gmail.com"
                      },
                      "event_link": {
                        "type": "string",
                        "example": "https://ticketflow.rs/events/2"
                      },
                      "total": {
                        "type": "number",
                        "example": 3500
                      },
                      "quantity": {
                        "type": "number",
                        "example": 1
                      }
                    },
                    "required": [
                      "event_title",
                      "seller_full_name",
                      "seller_email",
                      "event_link",
                      "total",
                      "quantity"
                    ]
                  }
                }
              },
              "required": [
                "to",
                "full_name",
                "orders"
              ]
            }
          }
        ],
        "responses": {
          "200": {
            "description": "OK"
          },
          "500": {
            "description": "Internal Server Error"
          }
        }
      }
    },
    "/cart/{id}": {
      "get": {
        "tags": [
          "Cart"
        ],
        "description": "",
        "parameters": [
          {
            "name": "id",
            "in": "path",
            "required": true,
            "type": "string"
          }
        ],
        "responses": {
          "200": {
            "description": "OK"
          },
          "500": {
            "description": "Internal Server Error"
          }
        }
      }
    },
    "/cart": {
      "post": {
        "tags": [
          "Cart"
        ],
        "description": "",
        "parameters": [
          {
            "name": "body",
            "in": "body",
            "schema": {
              "type": "object",
              "properties": {
                "userId": {
                  "type": "string",
                  "example": "user_29w83sxmXXNGwOuEthce5gg56Fee"
                },
                "offerId": {
                  "type": "number",
                  "example": 3
                },
                "quantity": {
                  "type": "number",
                  "example": 2
                }
              },
              "required": [
                "userId",
                "offerId",
                "quantity"
              ]
            }
          }
        ],
        "responses": {
          "200": {
            "description": "OK"
          },
          "500": {
            "description": "Internal Server Error"
          }
        }
      }
    }
  }
}